TCN/__init__.py
TCN/tcn.py
astar_tcn-0.0.1.dist-info/DESCRIPTION.rst
astar_tcn-0.0.1.dist-info/METADATA
astar_tcn-0.0.1.dist-info/RECORD
astar_tcn-0.0.1.dist-info/WHEEL
astar_tcn-0.0.1.dist-info/metadata.json
astar_tcn-0.0.1.dist-info/top_level.txt
