Metadata-Version: 2.0
Name: astar-tcn
Version: 0.0.1
Summary: tcn package
Home-page: https://github.com/ASTARCHEN/TCN
Author: A.Star
Author-email: astar@snowland.ltd
License: Apache v2.0
Platform: all
Classifier: Development Status :: 4 - Beta
Classifier: Operating System :: OS Independent
Classifier: Intended Audience :: Developers
Classifier: Programming Language :: Python
Classifier: Programming Language :: Python :: Implementation
Classifier: Programming Language :: Python :: 3
Classifier: Programming Language :: Python :: 3.6
Classifier: Programming Language :: Python :: 3.7
Classifier: Topic :: Software Development :: Libraries
Requires-Dist: pytorch
Requires-Dist: argparse
Requires-Dist: numpy
